AUTHORS
ChangeLog
LICENSE
README.rst
requirements.txt
setup.py
tox.ini
chipster_job_manager.egg-info/PKG-INFO
chipster_job_manager.egg-info/SOURCES.txt
chipster_job_manager.egg-info/dependency_links.txt
chipster_job_manager.egg-info/pbr.json
chipster_job_manager.egg-info/requires.txt
chipster_job_manager.egg-info/top_level.txt
etc/config.yaml.example
jobmanager/__init__.py
jobmanager/manager.py
jobmanager/models.py
jobmanager/run_flask.py
jobmanager/utils.py
jobmanager/tests/__init__.py
jobmanager/tests/test_jobs_db.py
jobmanager/tests/test_utils.py
jobmanager/www/__init__.py
jobmanager/www/httpserver.py
jobmanager/www/static/index.html
jobmanager/www/static/css/bootstrap-theme.min.css
jobmanager/www/static/css/bootstrap.min.css
jobmanager/www/static/css/dashboard.css
jobmanager/www/static/fonts/glyphicons-halflings-regular.eot
jobmanager/www/static/fonts/glyphicons-halflings-regular.svg
jobmanager/www/static/fonts/glyphicons-halflings-regular.ttf
jobmanager/www/static/fonts/glyphicons-halflings-regular.woff
jobmanager/www/static/js/bootstrap.min.js
jobmanager/www/static/js/docs.min.js
jobmanager/www/static/js/ui-bootstrap-tpls-0.12.0.min.js
jobmanager/www/static/js/webadmin.js
jobmanager/www/static/views/dashboard.html
jobmanager/www/static/views/jobs.html
jobmanager/www/static/views/maintenance.html