Metadata-Version: 1.1
Name: chipster-job-manager
Version: 3.1.8
Summary: Manages long running jobs on Chipster platform
Home-page: UNKNOWN
Author: Harri Hämäläinen
Author-email: harri.hamalainen@csc.fi
License: MIT
Platform: UNKNOWN
Classifier: Development Status :: 4 - Beta
Classifier: Environment :: Console
Classifier: Operating System :: OS Independent
Classifier: Programming Language :: Python
